pysupawindow/__init__.py
pysupawindow/pysupawindow.py
pysupawindow-0.1.dist-info/LICENSE
pysupawindow-0.1.dist-info/METADATA
pysupawindow-0.1.dist-info/WHEEL
pysupawindow-0.1.dist-info/top_level.txt
pysupawindow-0.1.dist-info/RECORD
